Workbook

Sheet README
A1: Source-to-Target Mapping
A2: Project | B2: Legacy-to-FHIR Clinic Data Migration & Reconciliation Pipeline
A3: Source system | B3: Legacy clinic export (Synthea CSV, North Carolina, seed 12345) staged in SQL Server: FhirMigration.stg.*
A4: Target system | B4: FHIR R4 server (HAPI public test server, https://hapi.fhir.org/baseR4). Synthetic data only, no PHI.
A5: Version / status | B5: v0.1 DRAFT, for review
A6: Prepared by | B6: Kepha
A7: Reviewed / signed off by | B7: (pending)
A9: What this workbook is
A10: Purpose | B10: Defines, field by field, how each legacy column becomes a FHIR element, which rule transforms it, and what happens when the value is bad. The transform script (src/transform.py) must follow this document exactly. In a real migration this is reviewed and signed off BEFORE transform code is written.
A12: Tabs
A13: Patient_Map / Encounter_Map / Condition_Map | B13: One row per source column. Every source column appears, including the ones we deliberately do NOT migrate, so nothing is silently lost.
A14: Value_Maps | B14: Code crosswalks: legacy value -> FHIR code (e.g. M -> male).
A15: Validation_Rules | B15: Every check the pipeline runs, its action (Reject / Fix / Flag), and which planted error it is designed to catch.
A16: Decisions_Log | B16: Open questions and the choice made. Edit the blue cells as you decide.
A17: Summary | B17: Live counts of mapped vs. not-migrated columns (formulas).
A19: Status values
A20: Mapped | B20: Source value is copied/transformed into a FHIR element.
A21: Constant | B21: FHIR element filled with a fixed value (no source column), e.g. the project tag.
A22: Derived | B22: FHIR element calculated from one or more source columns (e.g. status from STOP date).
A23: Not migrated | B23: Deliberately left behind (data minimization, financial, or out of scope). The reason is in 'Why / notes'.
A24: Deferred | B24: Wanted, but planned for a later phase.
A26: Action values (Validation_Rules)
A27: Reject | B27: Record is NOT loaded; written to the rejected_records table with the rule ID and reason.
A28: Fix | B28: Value is corrected automatically (e.g. date format); the fix is logged.
A29: Flag | B29: Record IS loaded, but listed on the data-quality exceptions report for staff follow-up.
A31: Colour key
A32: Blue text | B32: Cells you are expected to review or edit (decisions, owners, status).

Sheet Summary
A1: Table | B1: Mapped | C1: Constant | D1: Derived | E1: Deferred | F1: Not migrated | G1: Total rows
A2: Patient | B2: =COUNTIF(Patient_Map!$E:$E,"Mapped") -> 16 | C2: =COUNTIF(Patient_Map!$E:$E,"Constant") -> 2 | D2: =COUNTIF(Patient_Map!$E:$E,"Derived") -> 0 | E2: =COUNTIF(Patient_Map!$E:$E,"Deferred") -> 2 | F2: =COUNTIF(Patient_Map!$E:$E,"Not migrated") -> 9 | G2: =COUNTA(Patient_Map!$A:$A)-1 -> 29
A3: Encounter | B3: =COUNTIF(Encounter_Map!$E:$E,"Mapped") -> 9 | C3: =COUNTIF(Encounter_Map!$E:$E,"Constant") -> 1 | D3: =COUNTIF(Encounter_Map!$E:$E,"Derived") -> 1 | E3: =COUNTIF(Encounter_Map!$E:$E,"Deferred") -> 2 | F3: =COUNTIF(Encounter_Map!$E:$E,"Not migrated") -> 4 | G3: =COUNTA(Encounter_Map!$A:$A)-1 -> 17
A4: Condition | B4: =COUNTIF(Condition_Map!$E:$E,"Mapped") -> 7 | C4: =COUNTIF(Condition_Map!$E:$E,"Constant") -> 3 | D4: =COUNTIF(Condition_Map!$E:$E,"Derived") -> 2 | E4: =COUNTIF(Condition_Map!$E:$E,"Deferred") -> 1 | F4: =COUNTIF(Condition_Map!$E:$E,"Not migrated") -> 0 | G4: =COUNTA(Condition_Map!$A:$A)-1 -> 13
A5: All tables | B5: =SUM(B2:B4) -> 32 | C5: =SUM(C2:C4) -> 6 | D5: =SUM(D2:D4) -> 3 | E5: =SUM(E2:E4) -> 5 | F5: =SUM(F2:F4) -> 13 | G5: =SUM(G2:G4) -> 59
A7: Validation rules
A8: Reject | B8: =COUNTIF(Validation_Rules!$D:$D,"Reject") -> 9
A9: Reject (cascade) | B9: =COUNTIF(Validation_Rules!$D:$D,"Reject (cascade)") -> 2
A10: Fix | B10: =COUNTIF(Validation_Rules!$D:$D,"Fix") -> 3
A11: Flag | B11: =COUNTIF(Validation_Rules!$D:$D,"Flag") -> 5
A12: Total rules | B12: =SUM(B8:B11) -> 19
A14: Rules that catch a planted error | B14: =COUNTIFS(Validation_Rules!$E$2:$E$100,"<>-",Validation_Rules!$E$2:$E$100,"<>") -> 7 | C14: These rules cover planted errors 1-9 (see answer key)

Sheet Patient_Map
A1: Map ID | B1: Source table | C1: Source column | D1: Sample value (from your data) | E1: Status | F1: Target FHIR resource | G1: Target FHIR element | H1: FHIR data type | I1: Required in FHIR? | J1: Transformation rule | K1: Validation rule ID | L1: Why / notes
A2: P01 | B2: patients | C2: Id | D2: d545798e-09a4-ef89-... | E2: Mapped | F2: Patient | G2: identifier[0].value | H2: Identifier | I2: No | J2: Copy as-is. identifier[0].system = urn:fhirmigration:legacy-patient-id. The FHIR server assigns its own Patient.id; the legacy Id is kept here so every record can be traced back to its source row. | K2: R-P05 | L2: Keep legacy IDs in a crosswalk table (legacy Id -> new FHIR id) for reconciliation and for linking encounters/conditions.
A3: P02 | B3: patients | C3: BIRTHDATE | D3: 1998-02-08 | E3: Mapped | F3: Patient | G3: birthDate | H3: date (YYYY-MM-DD) | I3: No* | J3: Accept YYYY-MM-DD as-is. Convert MM/DD/YYYY -> YYYY-MM-DD. Blank, unparseable or future date -> reject. | K3: R-P01, R-P02, R-P06 | L3: *Optional in base FHIR but required by our business rules: a patient cannot be safely identified or matched without DOB.
A4: P03 | B4: patients | C4: DEATHDATE | D4: 2019-08-25 | E4: Mapped | F4: Patient | G4: deceasedDateTime | H4: dateTime | I4: No | J4: If present, copy (YYYY-MM-DD). If blank, omit the element (patient living). | K4: R-P06 | L4: Must not be earlier than BIRTHDATE.
A5: P04 | B5: patients | C5: PREFIX | D5: Mrs. | E5: Mapped | F5: Patient | G5: name[0].prefix[0] | H5: string | I5: No | J5: Copy as-is if present.
A6: P05 | B6: patients | C6: FIRST | D6: Ashely524 | E6: Mapped | F6: Patient | G6: name[0].given[0] | H6: string | I6: No* | J6: Copy as-is. name[0].use = official. Blank -> reject. | K6: R-P07 | L6: Synthea adds digits to names on purpose (marks them as fake). Kept as-is; see Decisions_Log D1.
A7: P06 | B7: patients | C7: MIDDLE | D7: Maybelle917 | E7: Mapped | F7: Patient | G7: name[0].given[1] | H7: string | I7: No | J7: Copy as-is if present (second given name).
A8: P07 | B8: patients | C8: LAST | D8: Hickle134 | E8: Mapped | F8: Patient | G8: name[0].family | H8: string | I8: No* | J8: Copy as-is. Blank -> reject. | K8: R-P07 | L8: *US Core requires a family or given name.
A9: P08 | B9: patients | C9: SUFFIX | D9: (blank) | E9: Mapped | F9: Patient | G9: name[0].suffix[0] | H9: string | I9: No | J9: Copy as-is if present.
A10: P09 | B10: patients | C10: MAIDEN | D10: Brekke496 | E10: Mapped | F10: Patient | G10: name[1].family | H10: string | I10: No | J10: If present, add a second name with use = maiden and family = MAIDEN. | L10: Preserves name history, which helps patient matching.
A11: P10 | B11: patients | C11: MARITAL | D11: M | E11: Mapped | F11: Patient | G11: maritalStatus.coding[0] | H11: CodeableConcept | I11: No | J11: Look up in Value_Maps (Marital). Blank -> omit. Unknown code -> flag and omit. | K11: R-P08 | L11: Code system http://terminology.hl7.org/CodeSystem/v3-MaritalStatus
A12: P11 | B12: patients | C12: GENDER | D12: F | E12: Mapped | F12: Patient | G12: gender | H12: code | I12: No* | J12: Look up in Value_Maps (Gender): M -> male, F -> female. Anything else -> reject. | K12: R-P03 | L12: *Required by our business rules (needed for clinical quality measures).
A13: P12 | B13: patients | C13: ADDRESS | D13: 873 Mayer Avenue | E13: Mapped | F13: Patient | G13: address[0].line[0] | H13: string | I13: No | J13: Copy as-is. Blank -> load but flag as incomplete. address[0].use = home. | K13: R-P04 | L13: Missing address blocks mail-outs and patient matching but should not block care data.
A14: P13 | B14: patients | C14: CITY | D14: Gastonia | E14: Mapped | F14: Patient | G14: address[0].city | H14: string | I14: No | J14: Copy as-is.
A15: P14 | B15: patients | C15: STATE | D15: North Carolina | E15: Mapped | F15: Patient | G15: address[0].state | H15: string | I15: No | J15: Convert full name to 2-letter USPS code (North Carolina -> NC). See Value_Maps (State). | L15: US Core recommends USPS state codes.
A16: P15 | B16: patients | C16: COUNTY | D16: Gaston County | E16: Mapped | F16: Patient | G16: address[0].district | H16: string | I16: No | J16: Copy as-is. | L16: FHIR uses 'district' for county.
A17: P16 | B17: patients | C17: ZIP | D17: 28054 | E17: Mapped | F17: Patient | G17: address[0].postalCode | H17: string | I17: No | J17: Copy as text (keep leading zeros). | L17: Never store ZIP as a number: 02134 would become 2134.
A18: P17 | B18: patients | C18: (none) | E18: Constant | F18: Patient | G18: address[0].country | H18: string | I18: No | J18: Constant: US
A19: P18 | B19: patients | C19: FIPS | D19: 37071 | E19: Not migrated | L19: County FIPS code; not needed by the clinic. Can be re-derived from county.
A20: P19 | B20: patients | C20: LAT / LON | D20: 35.2128 / -81.3974 | E20: Not migrated | L20: Precise home coordinates are sensitive location data and not needed (data minimization).
A21: P20 | B21: patients | C21: RACE | D21: white | E21: Deferred | F21: Patient | G21: extension: us-core-race | H21: Extension | I21: No | J21: Phase 2: map to OMB race codes in the US Core race extension. | L21: Important for health-equity reporting; needs the US Core extension structure. See D3.
A22: P21 | B22: patients | C22: ETHNICITY | D22: nonhispanic | E22: Deferred | F22: Patient | G22: extension: us-core-ethnicity | H22: Extension | I22: No | J22: Phase 2: map to OMB ethnicity codes in the US Core ethnicity extension. | L22: See D3.
A23: P22 | B23: patients | C23: BIRTHPLACE | D23: Durham North Carolina US | E23: Not migrated | L23: Not needed for care at the clinic.
A24: P23 | B24: patients | C24: SSN | D24: (dropped in staging) | E24: Not migrated | L24: Data minimization (HIPAA): never migrate identifiers the new system doesn't need. Dropped before staging.
A25: P24 | B25: patients | C25: DRIVERS | D25: (dropped in staging) | E25: Not migrated | L25: Data minimization. Dropped before staging.
A26: P25 | B26: patients | C26: PASSPORT | D26: (dropped in staging) | E26: Not migrated | L26: Data minimization. Dropped before staging.
A27: P26 | B27: patients | C27: HEALTHCARE_EXPENSES | D27: 404910.07 | E27: Not migrated | L27: Financial summary, not clinical data. Out of scope.
A28: P27 | B28: patients | C28: HEALTHCARE_COVERAGE | D28: 97853.24 | E28: Not migrated | L28: Financial summary, not clinical data. Out of scope.
A29: P28 | B29: patients | C29: INCOME | D29: 41915 | E29: Not migrated | L29: Sensitive financial data; not needed (data minimization).
A30: P29 | B30: patients | C30: (none) | E30: Constant | F30: Patient | G30: meta.tag[0] | H30: Coding | I30: No | J30: Constant: system urn:fhirmigration:project, code kepha-migration-2026 | L30: Lets us find only OUR records on the shared public test server.

Sheet Encounter_Map
A1: Map ID | B1: Source table | C1: Source column | D1: Sample value (from your data) | E1: Status | F1: Target FHIR resource | G1: Target FHIR element | H1: FHIR data type | I1: Required in FHIR? | J1: Transformation rule | K1: Validation rule ID | L1: Why / notes
A2: E01 | B2: encounters | C2: Id | D2: (UUID) | E2: Mapped | F2: Encounter | G2: identifier[0].value | H2: Identifier | I2: No | J2: Copy as-is. identifier[0].system = urn:fhirmigration:legacy-encounter-id. | L2: Kept for traceability and for linking conditions to their visit.
A3: E02 | B3: encounters | C3: PATIENT | D3: (patient UUID) | E3: Mapped | F3: Encounter | G3: subject | H3: Reference(Patient) | I3: No* | J3: Look up the legacy patient Id in the patient crosswalk -> Reference(Patient/{new FHIR id}). Not found in source -> reject (orphan). Patient was rejected -> reject (cascade). | K3: R-E01, R-E04 | L3: *A visit with no patient is meaningless; required by our rules.
A4: E03 | B4: encounters | C4: START | D4: 2019-08-25T10:00:00Z | E4: Mapped | F4: Encounter | G4: period.start | H4: dateTime | I4: No* | J4: Copy as-is (ISO 8601 with time zone). Blank -> reject. | K4: R-E05
A5: E04 | B5: encounters | C5: STOP | D5: 2019-08-25T10:30:00Z | E5: Mapped | F5: Encounter | G5: period.end | H5: dateTime | I5: No | J5: Copy as-is if present. STOP earlier than START -> flag. | K5: R-E02
A6: E05 | B6: encounters | C6: (STOP) | E6: Derived | F6: Encounter | G6: status | H6: code | I6: Yes | J6: STOP present -> finished; STOP blank -> in-progress. | L6: status is REQUIRED (1..1) in FHIR R4.
A7: E06 | B7: encounters | C7: ENCOUNTERCLASS | D7: wellness | E7: Mapped | F7: Encounter | G7: class | H7: Coding | I7: Yes | J7: Look up in Value_Maps (Encounter class), e.g. wellness -> AMB, emergency -> EMER, inpatient -> IMP. Not in the map -> reject. | K7: R-E03 | L7: class is REQUIRED (1..1) in FHIR R4. System http://terminology.hl7.org/CodeSystem/v3-ActCode. See D2.
A8: E07 | B8: encounters | C8: CODE | D8: 162673000 | E8: Mapped | F8: Encounter | G8: type[0].coding[0].code | H8: CodeableConcept | I8: No | J8: Copy as-is. type[0].coding[0].system = http://snomed.info/sct. | L8: SNOMED CT code for the kind of visit.
A9: E08 | B9: encounters | C9: DESCRIPTION | D9: General examination of patient (procedure) | E9: Mapped | F9: Encounter | G9: type[0].coding[0].display | H9: string | I9: No | J9: Copy as-is; also copy to type[0].text.
A10: E09 | B10: encounters | C10: REASONCODE | D10: 72892002 | E10: Mapped | F10: Encounter | G10: reasonCode[0].coding[0].code | H10: CodeableConcept | I10: No | J10: If present, copy; system = http://snomed.info/sct. | L10: Why the patient came in.
A11: E10 | B11: encounters | C11: REASONDESCRIPTION | D11: Normal pregnancy | E11: Mapped | F11: Encounter | G11: reasonCode[0].coding[0].display | H11: string | I11: No | J11: If present, copy; also copy to reasonCode[0].text.
A12: E11 | B12: encounters | C12: ORGANIZATION | D12: (UUID) | E12: Deferred | F12: Encounter | G12: serviceProvider | H12: Reference(Organization) | I12: No | J12: Phase 2: migrate Organization resources first, then link. | L12: Organizations are not migrated in v1 (see D4).
A13: E12 | B13: encounters | C13: PROVIDER | D13: (UUID) | E13: Deferred | F13: Encounter | G13: participant[0].individual | H13: Reference(Practitioner) | I13: No | J13: Phase 2: migrate Practitioner resources first, then link. | L13: See D4.
A14: E13 | B14: encounters | C14: PAYER | D14: (UUID) | E14: Not migrated | L14: Billing data belongs in Coverage/Claim resources. Out of scope for this clinical migration.
A15: E14 | B15: encounters | C15: BASE_ENCOUNTER_COST | D15: 129.16 | E15: Not migrated | L15: Financial. Out of scope (would map to Claim / ExplanationOfBenefit).
A16: E15 | B16: encounters | C16: TOTAL_CLAIM_COST | D16: 129.16 | E16: Not migrated | L16: Financial. Out of scope.
A17: E16 | B17: encounters | C17: PAYER_COVERAGE | D17: 69.16 | E17: Not migrated | L17: Financial. Out of scope.
A18: E17 | B18: encounters | C18: (none) | E18: Constant | F18: Encounter | G18: meta.tag[0] | H18: Coding | I18: No | J18: Constant: system urn:fhirmigration:project, code kepha-migration-2026

Sheet Condition_Map
A1: Map ID | B1: Source table | C1: Source column | D1: Sample value (from your data) | E1: Status | F1: Target FHIR resource | G1: Target FHIR element | H1: FHIR data type | I1: Required in FHIR? | J1: Transformation rule | K1: Validation rule ID | L1: Why / notes
A2: C01 | B2: conditions | C2: PATIENT + ENCOUNTER + CODE + START | D2: (composite) | E2: Derived | F2: Condition | G2: identifier[0].value | H2: Identifier | I2: No | J2: conditions.csv has no Id column, so build a legacy key: PATIENT|ENCOUNTER|CODE|START. identifier[0].system = urn:fhirmigration:legacy-condition-key. | K2: R-C05 | L2: Needed for traceability and duplicate detection. See D5.
A3: C02 | B3: conditions | C3: PATIENT | D3: (patient UUID) | E3: Mapped | F3: Condition | G3: subject | H3: Reference(Patient) | I3: Yes | J3: Look up in the patient crosswalk -> Reference(Patient/{new FHIR id}). Not found or patient rejected -> reject. | K3: R-C02 | L3: subject is REQUIRED (1..1) in FHIR R4.
A4: C03 | B4: conditions | C4: ENCOUNTER | D4: (encounter UUID) | E4: Mapped | F4: Condition | G4: encounter | H4: Reference(Encounter) | I4: No | J4: Look up in the encounter crosswalk -> Reference(Encounter/{new FHIR id}). Not found or encounter rejected -> load WITHOUT the link and flag. | K4: R-C03 | L4: The diagnosis is still clinically valid even if its visit could not be migrated.
A5: C04 | B5: conditions | C5: START | D5: 2015-10-06 | E5: Mapped | F5: Condition | G5: onsetDateTime | H5: dateTime | I5: No | J5: Copy as-is. Blank -> load and flag. | K5: R-C04
A6: C05 | B6: conditions | C6: STOP | D6: (blank) | E6: Mapped | F6: Condition | G6: abatementDateTime | H6: dateTime | I6: No | J6: Copy if present; blank -> omit.
A7: C06 | B7: conditions | C7: (STOP) | E7: Derived | F7: Condition | G7: clinicalStatus | H7: CodeableConcept | I7: No* | J7: STOP blank -> active; STOP present -> resolved. System http://terminology.hl7.org/CodeSystem/condition-clinical. | L7: *FHIR rule con-4: if abatement is present, clinicalStatus must be inactive/resolved/remission.
A8: C07 | B8: conditions | C8: (none) | E8: Constant | F8: Condition | G8: verificationStatus | H8: CodeableConcept | I8: No | J8: Constant: confirmed (system http://terminology.hl7.org/CodeSystem/condition-ver-status). | L8: Diagnoses in the legacy record are treated as confirmed.
A9: C08 | B9: conditions | C9: (none) | E9: Constant | F9: Condition | G9: category[0] | H9: CodeableConcept | I9: No | J9: Constant: encounter-diagnosis (system http://terminology.hl7.org/CodeSystem/condition-category). | L9: These diagnoses were recorded during visits.
A10: C09 | B10: conditions | C10: SYSTEM | D10: SNOMED-CT | E10: Mapped | F10: Condition | G10: code.coding[0].system | H10: uri | I10: No | J10: Convert to the official URI: SNOMED-CT / blank -> http://snomed.info/sct; ICD-10-CM -> http://hl7.org/fhir/sid/icd-10-cm. Unknown -> reject. | K10: R-C06 | L10: A code is only meaningful together with its code system.
A11: C10 | B11: conditions | C11: CODE | D11: 44054006 | E11: Mapped | F11: Condition | G11: code.coding[0].code | H11: code | I11: No* | J11: Copy as-is. Blank -> reject. | K11: R-C01 | L11: *A diagnosis with no code is unusable for reporting and billing.
A12: C11 | B12: conditions | C12: DESCRIPTION | D12: Diabetes mellitus type 2 (disorder) | E12: Mapped | F12: Condition | G12: code.coding[0].display | H12: string | I12: No | J12: Copy as-is; also copy to code.text.
A13: C12 | B13: conditions | C13: (none) | E13: Constant | F13: Condition | G13: meta.tag[0] | H13: Coding | I13: No | J13: Constant: system urn:fhirmigration:project, code kepha-migration-2026
A14: C13 | B14: conditions | C14: (future) | E14: Deferred | F14: Condition | G14: code.coding[1] | H14: Coding | I14: No | J14: Phase 2: add an ICD-10-CM translation alongside SNOMED (SNOMED -> ICD-10-CM crosswalk). | L14: Shows coding expertise; clinics bill with ICD-10-CM. See D6.

Sheet Value_Maps
A1: Map name | B1: Source column | C1: Legacy value | D1: FHIR value | E1: FHIR code system | F1: Notes
A2: Gender | B2: GENDER | C2: M | D2: male | E2: http://hl7.org/fhir/administrative-gender
A3: Gender | B3: GENDER | C3: F | D3: female | E3: http://hl7.org/fhir/administrative-gender
A4: Gender | B4: GENDER | C4: (anything else) | D4: REJECT | F4: Rule R-P03
A5: Marital | B5: MARITAL | C5: M | D5: M (Married) | E5: http://terminology.hl7.org/CodeSystem/v3-MaritalStatus
A6: Marital | B6: MARITAL | C6: S | D6: S (Never Married) | E6: http://terminology.hl7.org/CodeSystem/v3-MaritalStatus
A7: Marital | B7: MARITAL | C7: D | D7: D (Divorced) | E7: http://terminology.hl7.org/CodeSystem/v3-MaritalStatus
A8: Marital | B8: MARITAL | C8: W | D8: W (Widowed) | E8: http://terminology.hl7.org/CodeSystem/v3-MaritalStatus
A9: Marital | B9: MARITAL | C9: (blank) | D9: (omit element)
A10: Encounter class | B10: ENCOUNTERCLASS | C10: ambulatory | D10: AMB (ambulatory) | E10: http://terminology.hl7.org/CodeSystem/v3-ActCode
A11: Encounter class | B11: ENCOUNTERCLASS | C11: wellness | D11: AMB (ambulatory) | E11: http://terminology.hl7.org/CodeSystem/v3-ActCode
A12: Encounter class | B12: ENCOUNTERCLASS | C12: outpatient | D12: AMB (ambulatory) | E12: http://terminology.hl7.org/CodeSystem/v3-ActCode
A13: Encounter class | B13: ENCOUNTERCLASS | C13: urgentcare | D13: AMB (ambulatory) | E13: http://terminology.hl7.org/CodeSystem/v3-ActCode | F13: Review: see D2
A14: Encounter class | B14: ENCOUNTERCLASS | C14: emergency | D14: EMER (emergency) | E14: http://terminology.hl7.org/CodeSystem/v3-ActCode
A15: Encounter class | B15: ENCOUNTERCLASS | C15: inpatient | D15: IMP (inpatient encounter) | E15: http://terminology.hl7.org/CodeSystem/v3-ActCode
A16: Encounter class | B16: ENCOUNTERCLASS | C16: snf | D16: NONAC (inpatient non-acute) | E16: http://terminology.hl7.org/CodeSystem/v3-ActCode | F16: Skilled nursing facility. Review: see D2
A17: Encounter class | B17: ENCOUNTERCLASS | C17: hospice | D17: NONAC (inpatient non-acute) | E17: http://terminology.hl7.org/CodeSystem/v3-ActCode | F17: Review: see D2
A18: Encounter class | B18: ENCOUNTERCLASS | C18: home | D18: HH (home health) | E18: http://terminology.hl7.org/CodeSystem/v3-ActCode
A19: Encounter class | B19: ENCOUNTERCLASS | C19: virtual | D19: VR (virtual) | E19: http://terminology.hl7.org/CodeSystem/v3-ActCode
A20: Encounter class | B20: ENCOUNTERCLASS | C20: (anything else) | D20: REJECT | F20: Rule R-E03
A21: State | B21: STATE | C21: North Carolina | D21: NC | E21: USPS state codes | F21: Script holds the full 50-state table
A22: Condition clinical status | B22: STOP (derived) | C22: (blank) | D22: active | E22: http://terminology.hl7.org/CodeSystem/condition-clinical
A23: Condition clinical status | B23: STOP (derived) | C23: (date present) | D23: resolved | E23: http://terminology.hl7.org/CodeSystem/condition-clinical
A24: Code system | B24: SYSTEM | C24: SNOMED-CT or blank | D24: http://snomed.info/sct
A25: Code system | B25: SYSTEM | C25: ICD-10-CM | D25: http://hl7.org/fhir/sid/icd-10-cm

Sheet Validation_Rules
A1: Rule ID | B1: Table | C1: Check | D1: Action | E1: Planted error # (answer key row) | F1: Answer key error_type | G1: How it is tested (SQL / logic)
A2: R-P01 | B2: patients | C2: BIRTHDATE is blank | D2: Reject | E2: 1, 2 | F2: missing_required_value | G2: BIRTHDATE IS NULL
A3: R-P02 | B3: patients | C3: BIRTHDATE not in YYYY-MM-DD format | D3: Fix | E3: 3 | F3: nonstandard_date_format | G3: Convert MM/DD/YYYY to YYYY-MM-DD; if it can't be parsed, Reject
A4: R-P03 | B4: patients | C4: GENDER not M or F | D4: Reject | E4: 4 | F4: invalid_code | G4: GENDER NOT IN ('M','F')
A5: R-P04 | B5: patients | C5: ADDRESS is blank | D5: Flag | E5: 5, 6 | F5: missing_optional_value | G5: ADDRESS IS NULL
A6: R-P05 | B6: patients | C6: Same patient Id appears more than once | D6: Fix | E6: 7 | F6: duplicate_record | G6: Keep the first row, remove the extra copies, log each removal
A7: R-P06 | B7: patients | C7: BIRTHDATE in the future, or DEATHDATE before BIRTHDATE | D7: Reject | E7: - | F7: (not planted) | G7: Date logic check
A8: R-P07 | B8: patients | C8: FIRST or LAST is blank | D8: Reject | E8: - | F8: (not planted) | G8: FIRST IS NULL OR LAST IS NULL
A9: R-P08 | B9: patients | C9: MARITAL not in Value_Maps | D9: Flag | E9: - | F9: (not planted) | G9: Omit maritalStatus and flag
A10: R-E01 | B10: encounters | C10: PATIENT not found in the source patient list | D10: Reject | E10: 8 | F10: orphan_reference | G10: PATIENT NOT IN (SELECT Id FROM stg.patients)
A11: R-E02 | B11: encounters | C11: STOP earlier than START | D11: Flag | E11: - | F11: (not planted) | G11: STOP < START
A12: R-E03 | B12: encounters | C12: ENCOUNTERCLASS not in Value_Maps | D12: Reject | E12: - | F12: (not planted) | G12: class is required in FHIR
... A20: R-C06 | B20: conditions | C20: SYSTEM not recognised | D20: Reject | E20: - | F20: (not planted) | G20: See Value_Maps (Code system)
A22: Note on cascades: | C22: Rejecting 3 patients (rules R-P01, R-P03) also rejects their encounters and conditions (R-E04, R-C02). These are logged with their own rule IDs so the reconciliation can show: source rows = loaded + rejected (direct) + rejected (cascade) + duplicates removed.

Sheet Decisions_Log
A1: ID | B1: Question | C1: Decision | D1: Owner | E1: Status
A2: D1 | B2: Synthea adds digits to names (Ashely524). Strip them? | C2: Keep as-is. The digits mark the data as synthetic, and changing names would make field-level reconciliation harder. | D2: Kepha | E2: Decided
A3: D2 | B3: How should urgentcare, snf and hospice map to FHIR encounter class? | C3: urgentcare -> AMB; snf and hospice -> NONAC. Confirm with clinical stakeholders in a real project. | D3: Kepha | E3: Open
A4: D3 | B4: Migrate race and ethnicity? | C4: Deferred to phase 2 (needs US Core extensions with OMB codes). | D4: Kepha | E4: Decided
A5: D4 | B5: Migrate organizations and practitioners? | C5: Not in v1. Encounters load without serviceProvider/participant links. | D5: Kepha | E5: Decided
A6: D5 | B6: conditions.csv has no unique Id. How do we identify rows? | C6: Composite legacy key PATIENT|ENCOUNTER|CODE|START. | D6: Kepha | E6: Decided
A7: D6 | B7: Add ICD-10-CM codes alongside SNOMED? | C7: Phase 2 stretch goal (SNOMED -> ICD-10-CM crosswalk). | D7: Kepha | E7: Open
A8: D7 | B8: Encounters of rejected patients: reject or hold? | C8: Reject with a separate cascade rule ID (R-E04), so the counts reconcile and staff can re-run them once the patient is fixed. | D8: Kepha | E8: Decided
